{"Account Created.":"Tài khoản đã được tạo.","View in browser.":"Xem trong trình duyệt.","All Rights Reserved.":"Đã đăng ký Bản quyền.","Hello,":"Xin chào,","We are happy to register on our platform. To complete your registration, click on the button below.":"Chúng tôi rất vui khi đăng ký trên nền tảng của chúng tôi. Để hoàn tất đăng ký của bạn, hãy nhấp vào nút bên dưới.","Complete Registration":"Hoàn tất đăng ký","Yours sincerely,":"Trân trọng,","Account created.":"Tài khoản đã được tạo.","Activate Account.":"Kích hoạt tài khoản.","Use the code below to complete your request on our platform.":"Sử dụng mã bên dưới để hoàn thành yêu cầu của bạn trên nền tảng của chúng tôi.","Security Token":"Thẻ bảo mật","Security token generated.":"Đã tạo mã thông báo bảo mật.","Error generating security token.":"Lỗi khi tạo mã thông báo bảo mật.","Queried security token validation.":"Đã truy vấn xác thực mã thông báo bảo mật.","Error validating security token.":"Lỗi khi xác thực mã thông báo bảo mật.","Authentication profile created.":"Đã tạo hồ sơ xác thực.","User profile created.":"Hồ sơ người dùng đã được tạo.","Added image to user profile.":"Đã thêm hình ảnh vào hồ sơ người dùng.","Added image in authentication profile.":"Đã thêm hình ảnh trong hồ sơ xác thực.","Notification triggered.":"Thông báo được kích hoạt.","Invalid authentication model.":"Mô hình xác thực không hợp lệ.","Error registering authentication.":"Lỗi khi đăng ký xác thực.","Authentication not found.":"Không tìm thấy xác thực.","Authentication previously validated email and mobile.":"Xác thực đã xác thực trước đó email và điện thoại di động.","Authentication pending email validation.":"Xác thực đang chờ xác thực email.","Authentication pending cell validation.":"Xác thực đang chờ xác thực ô.","Error verifying user registration, invalid signature.":"Lỗi khi xác minh đăng ký người dùng, chữ ký không hợp lệ.","Error verifying user registration.":"Lỗi khi xác minh đăng ký người dùng.","Error loading permissions.":"Lỗi khi tải quyền.","Error logging in.":"Lỗi đăng nhập.","Authentication token generated.":"Đã tạo mã thông báo xác thực.","Login performed.":"Đăng nhập được thực hiện.","Error logging in, authentication did not complete registration.":"Lỗi đăng nhập, xác thực không hoàn thành đăng ký.","Error logging in, authentication blocked.":"Lỗi khi đăng nhập, xác thực bị chặn.","Error logging in, authentication not found.":"Lỗi khi đăng nhập, không tìm thấy xác thực.","Loaded datatable data.":"Đã tải dữ liệu có thể dữ liệu.","Error loading datatable data.":"Lỗi khi tải dữ liệu có thể dữ liệu.","Registry data loaded to be viewed or changed.":"Dữ liệu đăng ký được tải để được xem hoặc thay đổi.","Error loading registry data loaded to be viewed or changed.":"Lỗi khi tải dữ liệu đăng ký được tải để xem hoặc thay đổi.","Updated record.":"Đã cập nhật hồ sơ.","Error updating record.":"Lỗi khi cập nhật bản ghi.","Record deleted.":"Bản ghi đã bị xóa.","Error deleting record.":"Lỗi khi xóa bản ghi.","Registration carried out.":"Đăng ký được thực hiện.","Error when registering.":"Lỗi khi đăng ký.","Data validation error.":"Lỗi xác thực dữ liệu.","Without permission to register, authentication is logged.":"Nếu không có quyền đăng ký, xác thực được ghi lại.","Starting Tenant to create team in job.":"Bắt đầu người thuê để tạo nhóm trong công việc.","Created Team in job.":"Đã tạo Đội trong công việc.","Starting team in job.":"Đội ngũ bắt đầu vào công việc.","Created SubDomain in job.":"Đã tạo SubDomain trong công việc.","Created Team Config in job.":"Đã tạo cấu hình nhóm trong công việc.","Added image logo passed via URL.":"Biểu trưng hình ảnh đã thêm được chuyển qua URL.","Added image logo default.":"Đã thêm mặc định logo hình ảnh.","Added image login passed via URL.":"Đã thêm đăng nhập hình ảnh thông qua URL.","Added image logo default":"Đã thêm mặc định logo hình ảnh","Registered default form settings.":"Đã đăng ký cài đặt biểu mẫu mặc định.","Registered Permissions.":"Quyền đã đăng ký.","Error registering team in the job.":"Lỗi khi đăng ký nhóm trong công việc.","Password Recovery.":"Khôi phục mật khẩu.","Password Recovery":"Khôi phục mật khẩu","Click on the link below to retrieve your credentials on our website.":"Nhấp vào liên kết dưới đây để lấy thông tin đăng nhập của bạn trên trang web của chúng tôi.","Password recovery request valid for 60 minutes.":"Yêu cầu khôi phục mật khẩu có hiệu lực trong 60 phút."}